sqlmermaid.py
sqlmermaid-0.1.4.dist-info/LICENSE
sqlmermaid-0.1.4.dist-info/WHEEL
sqlmermaid-0.1.4.dist-info/METADATA
sqlmermaid-0.1.4.dist-info/RECORD
