Metadata-Version: 2.1
Name: sqlmermaid
Version: 0.1.4
Summary: Visualizing SQL databases
Author-email: Endre Márk Borza <endremborza@gmail.com>
Requires-Python: >=3.8
Requires-Dist: sqlalchemy>=2.0.0
Requires-Dist: branthebuilder[doc] ; extra == "doc"
Requires-Dist: sphinxcontrib-mermaid ; extra == "doc"
Requires-Dist: branthebuilder ; extra == "test"
Project-URL: Homepage, https://github.com/endremborza/sqlmermaid
Provides-Extra: doc
Provides-Extra: test
